{"NO_LEAF_OFF_IMAGERY":{"width":434,"height":361,"x":0,"y":0,"pixelRatio":1},"BLM_FILL":{"width":327,"height":325,"x":434,"y":0,"pixelRatio":1},"BOR_FILL":{"width":327,"height":325,"x":0,"y":361,"pixelRatio":1},"NPS_FILL":{"width":327,"height":325,"x":327,"y":361,"pixelRatio":1},"STATE_FILL":{"width":327,"height":325,"x":0,"y":686,"pixelRatio":1},"STATE_FOREST_FILL":{"width":327,"height":325,"x":327,"y":686,"pixelRatio":1},"STATE_FWP_FILL":{"width":327,"height":325,"x":0,"y":1011,"pixelRatio":1},"STATE_PARK_FILL":{"width":327,"height":325,"x":327,"y":1011,"pixelRatio":1},"TVA_FILL":{"width":327,"height":325,"x":654,"y":361,"pixelRatio":1},"USACE_FILL":{"width":327,"height":325,"x":981,"y":361,"pixelRatio":1},"USFS_FILL":{"width":327,"height":325,"x":1308,"y":361,"pixelRatio":1},"USFWS_FILL":{"width":327,"height":325,"x":654,"y":686,"pixelRatio":1},"EVENT_BADGE_RUT":{"width":88,"height":88,"x":1635,"y":361,"pixelRatio":1},"FIFTY_PROJECT":{"width":88,"height":88,"x":981,"y":686,"pixelRatio":1},"LEAVE_NO_TRACE_SPOTLIGHT":{"width":88,"height":88,"x":1069,"y":686,"pixelRatio":1},"CA-300-ICON":{"width":51,"height":78,"x":1157,"y":686,"pixelRatio":1},"GLACIER_FILL":{"width":60,"height":60,"x":1208,"y":686,"pixelRatio":1},"INTERMITTENT_WATER_FILL":{"width":60,"height":60,"x":1268,"y":686,"pixelRatio":1},"LANDCOVER_PATTERN":{"width":60,"height":60,"x":1328,"y":686,"pixelRatio":1},"SALT_FLAT_FILL":{"width":60,"height":60,"x":1388,"y":686,"pixelRatio":1},"WETLAND_FILL":{"width":60,"height":60,"x":1448,"y":686,"pixelRatio":1},"DU_GREEN":{"width":65,"height":46,"x":1508,"y":686,"pixelRatio":1},"SNOTEL_PIN_SELECTED":{"width":31,"height":46,"x":1573,"y":686,"pixelRatio":1},"trail-cam-direction-east":{"width":37,"height":46,"x":1604,"y":686,"pixelRatio":1},"trail-cam-direction-northeast":{"width":46,"height":46,"x":1641,"y":686,"pixelRatio":1},"trail-cam-direction-northwest":{"width":46,"height":46,"x":1687,"y":686,"pixelRatio":1},"trail-cam-direction-southeast":{"width":46,"height":46,"x":654,"y":1011,"pixelRatio":1},"trail-cam-direction-southwest":{"width":46,"height":46,"x":700,"y":1011,"pixelRatio":1},"trail-cam-direction-west":{"width":37,"height":46,"x":746,"y":1011,"pixelRatio":1},"BIKE_SELECTED":{"width":31,"height":45,"x":783,"y":1011,"pixelRatio":1},"CLIMB_SELECTED_BLACK":{"width":31,"height":45,"x":814,"y":1011,"pixelRatio":1},"DOVE":{"width":39,"height":45,"x":845,"y":1011,"pixelRatio":1},"HIKE_SELECTED":{"width":31,"height":45,"x":884,"y":1011,"pixelRatio":1},"trail-cam-black":{"width":40,"height":44,"x":915,"y":1011,"pixelRatio":1},"trail-cam-black-selected":{"width":40,"height":44,"x":955,"y":1011,"pixelRatio":1},"trail-cam-blue":{"width":40,"height":44,"x":995,"y":1011,"pixelRatio":1},"trail-cam-blue-selected":{"width":40,"height":44,"x":1035,"y":1011,"pixelRatio":1},"trail-cam-brown":{"width":40,"height":44,"x":1075,"y":1011,"pixelRatio":1},"trail-cam-brown-selected":{"width":40,"height":44,"x":1115,"y":1011,"pixelRatio":1},"trail-cam-cyan":{"width":40,"height":44,"x":1155,"y":1011,"pixelRatio":1},"trail-cam-cyan-selected":{"width":40,"height":44,"x":1195,"y":1011,"pixelRatio":1},"trail-cam-green":{"width":40,"height":44,"x":1235,"y":1011,"pixelRatio":1},"trail-cam-green-selected":{"width":40,"height":44,"x":1275,"y":1011,"pixelRatio":1},"trail-cam-grey":{"width":40,"height":44,"x":1315,"y":1011,"pixelRatio":1},"trail-cam-grey-selected":{"width":40,"height":44,"x":1355,"y":1011,"pixelRatio":1},"trail-cam-orange":{"width":40,"height":44,"x":1395,"y":1011,"pixelRatio":1},"trail-cam-orange-selected":{"width":40,"height":44,"x":1435,"y":1011,"pixelRatio":1},"trail-cam-purple":{"width":40,"height":44,"x":1475,"y":1011,"pixelRatio":1},"trail-cam-purple-selected":{"width":40,"height":44,"x":1515,"y":1011,"pixelRatio":1},"trail-cam-red":{"width":40,"height":44,"x":1555,"y":1011,"pixelRatio":1},"trail-cam-red-selected":{"width":40,"height":44,"x":1595,"y":1011,"pixelRatio":1},"trail-cam-white":{"width":40,"height":44,"x":1635,"y":1011,"pixelRatio":1},"trail-cam-white-selected":{"width":40,"height":44,"x":1675,"y":1011,"pixelRatio":1},"trail-cam-yellow":{"width":40,"height":44,"x":761,"y":0,"pixelRatio":1},"trail-cam-yellow-selected":{"width":40,"height":44,"x":801,"y":0,"pixelRatio":1},"SNOTEL_PIN_HOVER":{"width":43,"height":43,"x":841,"y":0,"pixelRatio":1},"AVALANCHE_FATALITY":{"width":40,"height":41,"x":884,"y":0,"pixelRatio":1},"AVALANCHE_OBSERVATION":{"width":40,"height":41,"x":924,"y":0,"pixelRatio":1},"SNOW_OBSERVATION":{"width":40,"height":41,"x":964,"y":0,"pixelRatio":1},"info-marker":{"width":30,"height":41,"x":1004,"y":0,"pixelRatio":1},"AVALANCHE_HUMAN_INVOLVED":{"width":40,"height":40,"x":1034,"y":0,"pixelRatio":1},"FEATURED_BIKE_PIN":{"width":32,"height":38,"x":1074,"y":0,"pixelRatio":1},"FEATURED_SKI_TOURING_PIN":{"width":32,"height":38,"x":1106,"y":0,"pixelRatio":1},"FEATURED_TRAIL_PIN":{"width":32,"height":38,"x":1138,"y":0,"pixelRatio":1},"PHEASANT":{"width":64,"height":38,"x":1170,"y":0,"pixelRatio":1},"FEATURED_CLIMB_PIN":{"width":30,"height":37,"x":1234,"y":0,"pixelRatio":1},"FEATURED_SNOWSHOEING_PIN":{"width":30,"height":37,"x":1264,"y":0,"pixelRatio":1},"FEATURED_XC_SKIING_PIN":{"width":30,"height":37,"x":1294,"y":0,"pixelRatio":1},"HAZARD":{"width":37,"height":37,"x":1324,"y":0,"pixelRatio":1},"SNOTEL_PIN":{"width":36,"height":37,"x":1361,"y":0,"pixelRatio":1},"WILDFIRE_ACTIVE":{"width":37,"height":37,"x":1397,"y":0,"pixelRatio":1},"highway-interstate-truck-1":{"width":26,"height":37,"x":1434,"y":0,"pixelRatio":1},"highway-interstate-truck-2":{"width":27,"height":37,"x":1460,"y":0,"pixelRatio":1},"trail-cam-direction-north":{"width":46,"height":37,"x":1487,"y":0,"pixelRatio":1},"trail-cam-direction-south":{"width":46,"height":37,"x":1533,"y":0,"pixelRatio":1},"CLOSURE_WILDLIFE":{"width":36,"height":36,"x":1579,"y":0,"pixelRatio":1},"DOTS_SPARSE_BLUE_DARK_FILL":{"width":36,"height":36,"x":1615,"y":0,"pixelRatio":1},"DOTS_SPARSE_GREEN_DARK_FILL":{"width":36,"height":36,"x":1651,"y":0,"pixelRatio":1},"DOTS_SPARSE_LIGHT_DARK":{"width":36,"height":36,"x":1687,"y":0,"pixelRatio":1},"DOTS_SPARSE_TAN_DARK_FILL":{"width":36,"height":36,"x":0,"y":1336,"pixelRatio":1},"FEATURED_SNOWMOBILE_PIN":{"width":30,"height":36,"x":36,"y":1336,"pixelRatio":1},"RMEF_LANDS":{"width":42,"height":36,"x":66,"y":1336,"pixelRatio":1},"SKI_DIFFICULTY_DIFFICULT":{"width":36,"height":36,"x":108,"y":1336,"pixelRatio":1},"USFW_SHIELD":{"width":36,"height":36,"x":144,"y":1336,"pixelRatio":1},"WILDFIRE_ACTIVE_MINOR":{"width":29,"height":36,"x":180,"y":1336,"pixelRatio":1},"highway-interstate-truck-3":{"width":32,"height":36,"x":209,"y":1336,"pixelRatio":1},"PATH":{"width":41,"height":35,"x":241,"y":1336,"pixelRatio":1},"PF_QF":{"width":41,"height":35,"x":282,"y":1336,"pixelRatio":1},"highway-us-business-1":{"width":25,"height":35,"x":323,"y":1336,"pixelRatio":1},"highway-us-business-2":{"width":25,"height":35,"x":348,"y":1336,"pixelRatio":1},"highway-us-business-3":{"width":31,"height":35,"x":373,"y":1336,"pixelRatio":1},"highway-us-truck-1":{"width":25,"height":35,"x":404,"y":1336,"pixelRatio":1},"highway-us-truck-2":{"width":25,"height":35,"x":429,"y":1336,"pixelRatio":1},"EVENT_START_FINISH":{"width":72,"height":34,"x":454,"y":1336,"pixelRatio":1},"highway-us-truck-3":{"width":31,"height":34,"x":526,"y":1336,"pixelRatio":1},"SKI_DIFFICULTY_EXTREME":{"width":53,"height":33,"x":557,"y":1336,"pixelRatio":1},"SKI_DIFFICULTY_DIFFICULT_EXTREME":{"width":53,"height":32,"x":610,"y":1336,"pixelRatio":1},"TRAIL_APPALACHIAN":{"width":33,"height":32,"x":663,"y":1336,"pixelRatio":1},"TRAIL_CONTINENTAL_DIVIDE":{"width":32,"height":32,"x":696,"y":1336,"pixelRatio":1},"TRAIL_PACIFIC_CREST":{"width":32,"height":32,"x":728,"y":1336,"pixelRatio":1},"WETLAND_FILL_SMALL":{"width":32,"height":32,"x":760,"y":1336,"pixelRatio":1},"DIAMONDS_YELLOW_WALKIN_FILL":{"width":30,"height":30,"x":792,"y":1336,"pixelRatio":1},"DOTS_GRAY_WALKIN_FILL":{"width":30,"height":30,"x":822,"y":1336,"pixelRatio":1},"DOTS_GREEN_LIGHT_FILL":{"width":30,"height":30,"x":852,"y":1336,"pixelRatio":1},"DOTS_RED_WALKIN_FILL":{"width":30,"height":30,"x":882,"y":1336,"pixelRatio":1},"DOTS_SPARSE_BLUE_FILL":{"width":30,"height":30,"x":912,"y":1336,"pixelRatio":1},"DOTS_SPARSE_GREEN_FILL":{"width":30,"height":30,"x":942,"y":1336,"pixelRatio":1},"DOTS_YELLOW_WALKIN_FILL":{"width":30,"height":30,"x":972,"y":1336,"pixelRatio":1},"GRAZING_ALLOTMENT_BLM_FILL":{"width":30,"height":30,"x":1002,"y":1336,"pixelRatio":1},"GRAZING_ALLOTMENT_FS_FILL":{"width":30,"height":30,"x":1032,"y":1336,"pixelRatio":1},"HASH_BLUE_FILL":{"width":30,"height":30,"x":1062,"y":1336,"pixelRatio":1},"HASH_BROWN_FILL":{"width":30,"height":30,"x":1092,"y":1336,"pixelRatio":1},"HASH_GRAY_WIDE_FILL":{"width":30,"height":30,"x":1122,"y":1336,"pixelRatio":1},"HASH_GREEN_DARK_FILL":{"width":30,"height":30,"x":1152,"y":1336,"pixelRatio":1},"HASH_GREEN_FILL":{"width":30,"height":30,"x":1182,"y":1336,"pixelRatio":1},"HASH_GREEN_LIGHT_FILL":{"width":30,"height":30,"x":1212,"y":1336,"pixelRatio":1},"HASH_PURPLE_FILL":{"width":30,"height":30,"x":1242,"y":1336,"pixelRatio":1},"HASH_RED_WIDE_FILL":{"width":30,"height":30,"x":1272,"y":1336,"pixelRatio":1},"HASH_YELLOW":{"width":30,"height":30,"x":1302,"y":1336,"pixelRatio":1},"NGO_FILL":{"width":30,"height":30,"x":1332,"y":1336,"pixelRatio":1},"SAFETY_ZONES_FILL":{"width":30,"height":30,"x":1362,"y":1336,"pixelRatio":1},"SLASH_WHITE_BLACK_FILL":{"width":30,"height":30,"x":1392,"y":1336,"pixelRatio":1},"TIMBER_BORDER":{"width":30,"height":30,"x":1422,"y":1336,"pixelRatio":1},"WILDERNESS_FILL_BACKCOUNTRY":{"width":30,"height":30,"x":1452,"y":1336,"pixelRatio":1},"WILDERNESS_FILL_HUNT":{"width":30,"height":30,"x":1482,"y":1336,"pixelRatio":1},"WILDERNESS_FILL_OFFROAD":{"width":30,"height":30,"x":1512,"y":1336,"pixelRatio":1},"WMA_FILL":{"width":30,"height":30,"x":1542,"y":1336,"pixelRatio":1},"RMEF_ACCESS_POINTS":{"width":17,"height":29,"x":1572,"y":1336,"pixelRatio":1},"BIKE_CIRCLE_COUNT":{"width":28,"height":28,"x":1589,"y":1336,"pixelRatio":1},"HIKE_CIRCLE_COUNT":{"width":28,"height":28,"x":1617,"y":1336,"pixelRatio":1},"OFFROAD-TRAIL-BADGE-CLOSED":{"width":51,"height":27,"x":1645,"y":1336,"pixelRatio":1},"OFFROAD-TRAIL-BADGE-OPEN":{"width":51,"height":27,"x":0,"y":1372,"pixelRatio":1},"ONEWAY_BLACK":{"width":20,"height":27,"x":51,"y":1372,"pixelRatio":1},"ONEWAY_BLUE":{"width":20,"height":27,"x":71,"y":1372,"pixelRatio":1},"ONEWAY_GREEN_HIGHLIGHT":{"width":20,"height":27,"x":91,"y":1372,"pixelRatio":1},"ONEWAY_ORANGE":{"width":20,"height":27,"x":111,"y":1372,"pixelRatio":1},"ONEWAY_PINK":{"width":20,"height":27,"x":131,"y":1372,"pixelRatio":1},"ONEWAY_RED":{"width":20,"height":27,"x":151,"y":1372,"pixelRatio":1},"SKI_DIFFICULTY_INTERMEDIATE":{"width":26,"height":27,"x":171,"y":1372,"pixelRatio":1},"SKI_DIFFICULTY_INTERMEDIATE_DIFFICULT":{"width":26,"height":27,"x":197,"y":1372,"pixelRatio":1},"SKI_DIFFICULTY_EASY":{"width":26,"height":26,"x":223,"y":1372,"pixelRatio":1},"SKI_DIFFICULTY_EASY_INTERMEDIATE":{"width":26,"height":26,"x":249,"y":1372,"pixelRatio":1},"highway-interstate-business-3":{"width":32,"height":26,"x":275,"y":1372,"pixelRatio":1},"DIVE_AREA":{"width":36,"height":25,"x":307,"y":1372,"pixelRatio":1},"OFFROAD-ALPINE":{"width":32,"height":25,"x":343,"y":1372,"pixelRatio":1},"OFFROAD-DESERT":{"width":32,"height":25,"x":375,"y":1372,"pixelRatio":1},"OFFROAD-FOREST":{"width":32,"height":25,"x":407,"y":1372,"pixelRatio":1},"OFFROAD-MUD":{"width":32,"height":25,"x":439,"y":1372,"pixelRatio":1},"OFFROAD-PLAINS":{"width":32,"height":25,"x":471,"y":1372,"pixelRatio":1},"OFFROAD-ROCKCRAWL":{"width":32,"height":25,"x":503,"y":1372,"pixelRatio":1},"OFFROAD-SAND":{"width":32,"height":25,"x":535,"y":1372,"pixelRatio":1},"OFFROAD-SLICKROCK":{"width":32,"height":25,"x":567,"y":1372,"pixelRatio":1},"OFFROAD-SNOWMOBILE":{"width":32,"height":25,"x":599,"y":1372,"pixelRatio":1},"highway-interstate-3":{"width":33,"height":25,"x":631,"y":1372,"pixelRatio":1},"highway-interstate-business-1":{"width":24,"height":25,"x":664,"y":1372,"pixelRatio":1},"highway-interstate-business-2":{"width":24,"height":25,"x":688,"y":1372,"pixelRatio":1},"AIRPORT":{"width":24,"height":24,"x":712,"y":1372,"pixelRatio":1},"AIRPORT_HDR":{"width":24,"height":24,"x":736,"y":1372,"pixelRatio":1},"AMPHITHEATER":{"width":24,"height":24,"x":760,"y":1372,"pixelRatio":1},"ARCHERY":{"width":24,"height":24,"x":784,"y":1372,"pixelRatio":1},"BAT_COUNTRY":{"width":48,"height":24,"x":808,"y":1372,"pixelRatio":1},"BEACH_ACCESS":{"width":24,"height":24,"x":856,"y":1372,"pixelRatio":1},"BIRD_VIEWING":{"width":24,"height":24,"x":880,"y":1372,"pixelRatio":1},"BLIND":{"width":24,"height":24,"x":904,"y":1372,"pixelRatio":1},"BLM_SHIELD":{"width":24,"height":24,"x":928,"y":1372,"pixelRatio":1},"BOAT_RAMP":{"width":24,"height":24,"x":952,"y":1372,"pixelRatio":1},"BREWERY":{"width":24,"height":24,"x":976,"y":1372,"pixelRatio":1},"BUS_STOP":{"width":24,"height":24,"x":1000,"y":1372,"pixelRatio":1},"CABIN":{"width":24,"height":24,"x":1024,"y":1372,"pixelRatio":1},"CAMPGROUND":{"width":24,"height":24,"x":1048,"y":1372,"pixelRatio":1},"CAMPSITE":{"width":24,"height":24,"x":1072,"y":1372,"pixelRatio":1},"CANOE_TRAILHEAD":{"width":24,"height":24,"x":1096,"y":1372,"pixelRatio":1},"CAVING":{"width":24,"height":24,"x":1120,"y":1372,"pixelRatio":1},"CLIMBING":{"width":24,"height":24,"x":1144,"y":1372,"pixelRatio":1},"CORRAL":{"width":24,"height":24,"x":1168,"y":1372,"pixelRatio":1},"DAYUSE":{"width":24,"height":24,"x":1192,"y":1372,"pixelRatio":1},"DISC_GOLF":{"width":24,"height":24,"x":1216,"y":1372,"pixelRatio":1},"DISTILLERY":{"width":24,"height":24,"x":1240,"y":1372,"pixelRatio":1},"DOCK":{"width":24,"height":24,"x":1264,"y":1372,"pixelRatio":1},"DRILLING_PLATFORM":{"width":24,"height":24,"x":1288,"y":1372,"pixelRatio":1},"ENTRANCE_STATION":{"width":24,"height":24,"x":1312,"y":1372,"pixelRatio":1},"EQUESTRIAN_TRAIL":{"width":24,"height":24,"x":1336,"y":1372,"pixelRatio":1},"EV_CHARGER":{"width":24,"height":24,"x":1360,"y":1372,"pixelRatio":1},"EXCLAMATION_POINT":{"width":24,"height":24,"x":1384,"y":1372,"pixelRatio":1},"FERRY":{"width":24,"height":24,"x":1408,"y":1372,"pixelRatio":1},"FIRST_AID":{"width":24,"height":24,"x":1432,"y":1372,"pixelRatio":1},"FISHING_ACCESS":{"width":24,"height":24,"x":1456,"y":1372,"pixelRatio":1},"FISHING_PIER":{"width":24,"height":24,"x":1480,"y":1372,"pixelRatio":1},"FISH_HATCHERY":{"width":24,"height":24,"x":1504,"y":1372,"pixelRatio":1},"GAS_STATION":{"width":24,"height":24,"x":1528,"y":1372,"pixelRatio":1},"GEO_MINE_AERIAL":{"width":24,"height":24,"x":1552,"y":1372,"pixelRatio":1},"GEO_MINE_TOPO":{"width":24,"height":24,"x":1576,"y":1372,"pixelRatio":1},"GEO_PASS_AERIAL":{"width":24,"height":24,"x":1600,"y":1372,"pixelRatio":1},"GEO_PASS_TOPO":{"width":24,"height":24,"x":1624,"y":1372,"pixelRatio":1},"GEO_PEAK_AERIAL":{"width":24,"height":24,"x":1648,"y":1372,"pixelRatio":1},"GEO_PEAK_TOPO":{"width":24,"height":24,"x":1672,"y":1372,"pixelRatio":1},"GEO_TOWER_AERIAL":{"width":24,"height":24,"x":1696,"y":1372,"pixelRatio":1},"GEO_TOWER_TOPO":{"width":24,"height":24,"x":1696,"y":1336,"pixelRatio":1},"GEYSER":{"width":24,"height":24,"x":0,"y":1399,"pixelRatio":1},"GOLF":{"width":24,"height":24,"x":24,"y":1399,"pixelRatio":1},"GUZZLER":{"width":24,"height":24,"x":48,"y":1399,"pixelRatio":1},"HAND_LAUNCH":{"width":24,"height":24,"x":72,"y":1399,"pixelRatio":1},"HANG_GLIDING":{"width":24,"height":24,"x":96,"y":1399,"pixelRatio":1},"HELIPORT":{"width":24,"height":24,"x":120,"y":1399,"pixelRatio":1},"INTERPRETIVE_SITE":{"width":24,"height":24,"x":144,"y":1399,"pixelRatio":1},"LICENSING_AGENT":{"width":24,"height":24,"x":168,"y":1399,"pixelRatio":1},"LIGHTHOUSE":{"width":24,"height":24,"x":192,"y":1399,"pixelRatio":1},"LODGE":{"width":24,"height":24,"x":216,"y":1399,"pixelRatio":1},"MARINA":{"width":24,"height":24,"x":240,"y":1399,"pixelRatio":1},"MOUNTAIN_BIKING":{"width":24,"height":24,"x":264,"y":1399,"pixelRatio":1},"NASA_FACILITY":{"width":24,"height":24,"x":288,"y":1399,"pixelRatio":1},"NON_ETHANOL":{"width":24,"height":24,"x":312,"y":1399,"pixelRatio":1},"NPS_SHIELD":{"width":24,"height":24,"x":336,"y":1399,"pixelRatio":1},"OBSERVATION_TOWER":{"width":24,"height":24,"x":360,"y":1399,"pixelRatio":1},"OBSTACLE":{"width":24,"height":24,"x":384,"y":1399,"pixelRatio":1},"OHV_AREA":{"width":24,"height":24,"x":408,"y":1399,"pixelRatio":1},"ONXMAPS":{"width":24,"height":24,"x":432,"y":1399,"pixelRatio":1},"PARKING_AREA":{"width":24,"height":24,"x":456,"y":1399,"pixelRatio":1},"PETROGLYPH":{"width":24,"height":24,"x":480,"y":1399,"pixelRatio":1},"PICNIC_AREA":{"width":24,"height":24,"x":504,"y":1399,"pixelRatio":1},"PICNIC_SHELTER":{"width":24,"height":24,"x":528,"y":1399,"pixelRatio":1},"PLACEHOLDER":{"width":24,"height":24,"x":552,"y":1399,"pixelRatio":1},"RACE_FLAG":{"width":24,"height":24,"x":576,"y":1399,"pixelRatio":1},"RACE_FLAGS":{"width":40,"height":24,"x":600,"y":1399,"pixelRatio":1},"RANGER_STATION":{"width":24,"height":24,"x":640,"y":1399,"pixelRatio":1},"RENTAL_SHOP":{"width":24,"height":24,"x":664,"y":1399,"pixelRatio":1},"REPAIR_SHOP":{"width":24,"height":24,"x":688,"y":1399,"pixelRatio":1},"RESTROOM":{"width":24,"height":24,"x":712,"y":1399,"pixelRatio":1},"ROADBLOCK":{"width":24,"height":24,"x":736,"y":1399,"pixelRatio":1},"ROCK_CRAWL_AREA":{"width":24,"height":24,"x":760,"y":1399,"pixelRatio":1},"RUINS":{"width":24,"height":24,"x":784,"y":1399,"pixelRatio":1},"RV_CAMPSITE":{"width":24,"height":24,"x":808,"y":1399,"pixelRatio":1},"SCENIC_AREA":{"width":24,"height":24,"x":832,"y":1399,"pixelRatio":1},"SEAPLANE_BASE":{"width":24,"height":24,"x":856,"y":1399,"pixelRatio":1},"SHELTER":{"width":24,"height":24,"x":880,"y":1399,"pixelRatio":1},"SHOOTING_RANGE":{"width":24,"height":24,"x":904,"y":1399,"pixelRatio":1},"SIGNIN_BOX":{"width":25,"height":24,"x":928,"y":1399,"pixelRatio":1},"SKI_AREA":{"width":24,"height":24,"x":953,"y":1399,"pixelRatio":1},"SNOWMOBILE":{"width":24,"height":24,"x":977,"y":1399,"pixelRatio":1},"SNO_PARK":{"width":24,"height":24,"x":1001,"y":1399,"pixelRatio":1},"SOUVENIRS":{"width":24,"height":24,"x":1025,"y":1399,"pixelRatio":1},"SQUARE_BLACK":{"width":24,"height":24,"x":1049,"y":1399,"pixelRatio":1},"STOCK_TANK":{"width":24,"height":24,"x":1073,"y":1399,"pixelRatio":1},"SURF_AREA":{"width":24,"height":24,"x":1097,"y":1399,"pixelRatio":1},"SWIMMING":{"width":24,"height":24,"x":1121,"y":1399,"pixelRatio":1},"TELEPHONE":{"width":24,"height":24,"x":1145,"y":1399,"pixelRatio":1},"TRAILHEAD":{"width":24,"height":24,"x":1169,"y":1399,"pixelRatio":1},"TRAIN_STATION":{"width":24,"height":24,"x":1193,"y":1399,"pixelRatio":1},"USFS_SHIELD":{"width":24,"height":24,"x":1217,"y":1399,"pixelRatio":1},"VISITOR_CENTER":{"width":24,"height":24,"x":1241,"y":1399,"pixelRatio":1},"WARMING_HUT":{"width":24,"height":24,"x":1265,"y":1399,"pixelRatio":1},"WATERFALL":{"width":24,"height":24,"x":1289,"y":1399,"pixelRatio":1},"WIND_SURFING":{"width":24,"height":24,"x":1313,"y":1399,"pixelRatio":1},"WMA":{"width":24,"height":24,"x":1337,"y":1399,"pixelRatio":1},"WRECK":{"width":24,"height":24,"x":1361,"y":1399,"pixelRatio":1},"XC_SKIING":{"width":24,"height":24,"x":1385,"y":1399,"pixelRatio":1},"highway-interstate-1":{"width":23,"height":24,"x":1409,"y":1399,"pixelRatio":1},"highway-interstate-2":{"width":25,"height":24,"x":1432,"y":1399,"pixelRatio":1},"wind-bubble-large-e":{"width":128,"height":24,"x":1457,"y":1399,"pixelRatio":1},"wind-bubble-large-n":{"width":128,"height":24,"x":1585,"y":1399,"pixelRatio":1},"wind-bubble-large-ne":{"width":128,"height":24,"x":0,"y":1423,"pixelRatio":1},"wind-bubble-large-nw":{"width":128,"height":24,"x":128,"y":1423,"pixelRatio":1},"wind-bubble-large-offline":{"width":128,"height":24,"x":256,"y":1423,"pixelRatio":1},"wind-bubble-large-s":{"width":128,"height":24,"x":384,"y":1423,"pixelRatio":1},"wind-bubble-large-se":{"width":128,"height":24,"x":512,"y":1423,"pixelRatio":1},"wind-bubble-large-sw":{"width":128,"height":24,"x":640,"y":1423,"pixelRatio":1},"wind-bubble-large-w":{"width":128,"height":24,"x":768,"y":1423,"pixelRatio":1},"wind-bubble-small-e":{"width":70,"height":24,"x":896,"y":1423,"pixelRatio":1},"wind-bubble-small-n":{"width":70,"height":24,"x":966,"y":1423,"pixelRatio":1},"wind-bubble-small-ne":{"width":70,"height":24,"x":1036,"y":1423,"pixelRatio":1},"wind-bubble-small-nw":{"width":70,"height":24,"x":1106,"y":1423,"pixelRatio":1},"wind-bubble-small-offline":{"width":70,"height":24,"x":1176,"y":1423,"pixelRatio":1},"wind-bubble-small-s":{"width":70,"height":24,"x":1246,"y":1423,"pixelRatio":1},"wind-bubble-small-se":{"width":70,"height":24,"x":1316,"y":1423,"pixelRatio":1},"wind-bubble-small-sw":{"width":70,"height":24,"x":1386,"y":1423,"pixelRatio":1},"wind-bubble-small-w":{"width":70,"height":24,"x":1456,"y":1423,"pixelRatio":1},"BIKE_CIRCLE":{"width":23,"height":23,"x":1713,"y":1399,"pixelRatio":1},"CLIMB_CIRCLE":{"width":23,"height":23,"x":1526,"y":1423,"pixelRatio":1},"HIKE_CIRCLE":{"width":23,"height":23,"x":1549,"y":1423,"pixelRatio":1},"POP_PLACE_CAPITAL_AERIAL":{"width":23,"height":23,"x":1572,"y":1423,"pixelRatio":1},"POP_PLACE_CAPITAL_TOPO":{"width":23,"height":23,"x":1595,"y":1423,"pixelRatio":1},"highway-us-1":{"width":23,"height":23,"x":1618,"y":1423,"pixelRatio":1},"highway-us-2":{"width":25,"height":23,"x":1641,"y":1423,"pixelRatio":1},"highway-us-3":{"width":31,"height":23,"x":1666,"y":1423,"pixelRatio":1},"trail-end":{"width":22,"height":23,"x":1697,"y":1423,"pixelRatio":1},"trail-start":{"width":22,"height":23,"x":0,"y":1447,"pixelRatio":1},"EVENT_FINISH":{"width":42,"height":22,"x":22,"y":1447,"pixelRatio":1},"EVENT_START":{"width":42,"height":22,"x":64,"y":1447,"pixelRatio":1},"PARK":{"width":22,"height":22,"x":106,"y":1447,"pixelRatio":1},"SNOWMOBILE_PARKING":{"width":22,"height":22,"x":128,"y":1447,"pixelRatio":1},"trail-loop":{"width":22,"height":22,"x":150,"y":1447,"pixelRatio":1},"highway-county-1":{"width":20,"height":21,"x":172,"y":1447,"pixelRatio":1},"highway-county-2":{"width":23,"height":21,"x":192,"y":1447,"pixelRatio":1},"highway-county-3":{"width":29,"height":21,"x":215,"y":1447,"pixelRatio":1},"highway-county-4":{"width":36,"height":21,"x":244,"y":1447,"pixelRatio":1},"highway-state-1":{"width":22,"height":21,"x":280,"y":1447,"pixelRatio":1},"highway-state-2":{"width":26,"height":21,"x":302,"y":1447,"pixelRatio":1},"highway-state-3":{"width":29,"height":21,"x":328,"y":1447,"pixelRatio":1},"highway-state-4":{"width":36,"height":21,"x":357,"y":1447,"pixelRatio":1},"CLEARCUT_FILL":{"width":20,"height":20,"x":393,"y":1447,"pixelRatio":1},"HOTSPRING":{"width":16,"height":20,"x":413,"y":1447,"pixelRatio":1},"THINNING_FILL":{"width":20,"height":20,"x":429,"y":1447,"pixelRatio":1},"CHEVRONS_PURPLE":{"width":12,"height":19,"x":449,"y":1447,"pixelRatio":1},"BENCH":{"width":18,"height":18,"x":461,"y":1447,"pixelRatio":1},"CONCESSIONS":{"width":18,"height":18,"x":479,"y":1447,"pixelRatio":1},"FEE_SITE":{"width":18,"height":18,"x":497,"y":1447,"pixelRatio":1},"FIREWOOD":{"width":18,"height":18,"x":515,"y":1447,"pixelRatio":1},"FOOD_STORAGE":{"width":18,"height":18,"x":533,"y":1447,"pixelRatio":1},"FOOT_BRIDGE":{"width":18,"height":18,"x":551,"y":1447,"pixelRatio":1},"GAUGING_STATION":{"width":18,"height":18,"x":569,"y":1447,"pixelRatio":1},"GENERAL_STORE":{"width":18,"height":18,"x":587,"y":1447,"pixelRatio":1},"INFORMATION":{"width":18,"height":18,"x":605,"y":1447,"pixelRatio":1},"KENNEL":{"width":18,"height":18,"x":623,"y":1447,"pixelRatio":1},"LAUNDRY":{"width":18,"height":18,"x":641,"y":1447,"pixelRatio":1},"PLAYGROUND":{"width":18,"height":18,"x":659,"y":1447,"pixelRatio":1},"POTABLE_WATER":{"width":18,"height":18,"x":677,"y":1447,"pixelRatio":1},"RECYCLING":{"width":18,"height":18,"x":695,"y":1447,"pixelRatio":1},"RV_DUMP":{"width":18,"height":18,"x":713,"y":1447,"pixelRatio":1},"SHOWER":{"width":18,"height":18,"x":731,"y":1447,"pixelRatio":1},"TRASH":{"width":18,"height":18,"x":749,"y":1447,"pixelRatio":1},"WIFI":{"width":18,"height":18,"x":767,"y":1447,"pixelRatio":1},"EXIT":{"width":29,"height":16,"x":785,"y":1447,"pixelRatio":1},"GATE":{"width":23,"height":16,"x":814,"y":1447,"pixelRatio":1},"OFFROAD-GUIDED-TRAIL":{"width":16,"height":16,"x":837,"y":1447,"pixelRatio":1},"OFFROAD-SNOWMOBILE-GUIDED-TRAIL":{"width":16,"height":16,"x":853,"y":1447,"pixelRatio":1},"WATER_SOURCE":{"width":16,"height":16,"x":869,"y":1447,"pixelRatio":1},"TRAIL_BADGE_CLOSED":{"width":28,"height":15,"x":885,"y":1447,"pixelRatio":1},"TRAIL_BADGE_OPEN":{"width":28,"height":15,"x":913,"y":1447,"pixelRatio":1},"ARROW_WHITE_LINE":{"width":37,"height":14,"x":941,"y":1447,"pixelRatio":1},"POP_PLACE_AERIAL":{"width":14,"height":14,"x":978,"y":1447,"pixelRatio":1},"POP_PLACE_TOPO":{"width":12,"height":12,"x":992,"y":1447,"pixelRatio":1},"MILEAGE_POINT_SUMMER":{"width":11,"height":11,"x":1004,"y":1447,"pixelRatio":1},"POP_PLACE_CAPITAL":{"width":10,"height":10,"x":1015,"y":1447,"pixelRatio":1},"DOT_HOTSPOT":{"width":9,"height":9,"x":1025,"y":1447,"pixelRatio":1},"POP_PLACE":{"width":9,"height":9,"x":1034,"y":1447,"pixelRatio":1},"ARROW_GRAY":{"width":11,"height":7,"x":1043,"y":1447,"pixelRatio":1},"ARROW_WHITE":{"width":11,"height":7,"x":1054,"y":1447,"pixelRatio":1}}